{"id":18157,"date":"2019-12-09T12:18:47","title":"Тивиком: В Улан-Удэ открылась выставка «Портрет. Границы жанра»","slug":"tivikom-v-ulan-udye-otkrylas-vystavka","uri":"/2019/12/09/tivikom-v-ulan-udye-otkrylas-vystavka/","img":"","cat":[{"name":"СМИ о нас","databaseId":125}],"content":"<p>Центральная работа выставки «Портрет. Границы жанра» принадлежит Льву Лабок.<strong>&nbsp;«Ученики одной школы»</strong>&nbsp;&#8212; название говорящее.</p>\n<p><!--more--></p>\n<p>На картине друзья художника &#8212; известные ученики первой школы Улан-Удэ и её знаменитый директор Иван Арский, что слева. Затем два золотых медалиста, будущий главный дирижёр и худрук оперного театра Валерий Галсанов, прославленный боксёр Веллингтон Баранников, заслуженный архитектор России Владимир Бельгаев. Полотно как будто обрывается, показывая, что замечательных выпускников у школы немало и по сей день.</p>\n<p><a href=\"https://tvcom-tv.ru/v-ulan-ude-otkryilas-vyistavka-%C2%ABportret.-graniczyi-zhanra%C2%BB.html\">https://tvcom-tv.ru/v-ulan-ude-otkryilas-vyistavka-%C2%ABportret.-graniczyi-zhanra%C2%BB.html</a></p>\n"}