{"id":18544,"date":"2020-01-16T07:16:27","title":"В Улан-Удэ открылась выставка к 105-летию со дня рождения Андрея Модогоева","slug":"v-ulan-udye-otkrylas-vystavka-k-105-letiyu","uri":"/2020/01/16/v-ulan-udye-otkrylas-vystavka-k-105-letiyu/","img":"http://muzeyrb.ru/wp-content/uploads/2020/01/image-15-01-20-06-14-1.jpeg","cat":[{"name":"Новости","databaseId":1}],"content":"<p>15 января в Музее истории им. М.Н. Хангалова открылась выставка «Человек-эпоха», посвященная 105-летию со дня рождения выдающегося государственного и политического деятеля Андрея Урупхеевича Модогоева, руководившего республикой с 1962 по 1984 годы.</p>\n<p><!--more--></p>\n<p>Открытие выставки вызвало значительный интерес – в фойе музея собралось очень много народу. На открытии выставки присутствовали родные и близкие Андрея Урупхеевича, а также те, кто знал его лично, в том числе видные политические деятели в прошлом. В их числе были первый президент Бурятии Леонид Потапов, бывшие члены республиканского правительства Владимир Прокопьев, Владимир Агалов, ветераны производства Ратмир Мухаров, депутаты Народного Хурала РБ Андреян Зыбынов, Баир Цыренов и многие другие.</p>\n<p>С приветственным словом перед присутствующими выступила министр культуры Бурятии Соелма Дагаева.</p>\n<p>– Сколько я помню себя, столько мы слышим целые придания о том, каким замечательным человеком был Андрей Урупхеевич Модогоев. Он помнил по имени и отчеству каждого животновода, каждого работника, с которым он встречался. Отлично разбирался в искусстве и культуре, помогал писателям, артистам, поднимал искусство Бурятии. Мы открываем выставку, которая представит кадры съемок Андрея Урупхеевича, его личные вещи и другие экспонаты, – отметила министр культуры Бурятии.</p>\n<p>Также Соелма Баяртуевна сообщила, что в этом году в республике, как и по всей стране, пройдут юбилейные мероприятия в честь 75-летия Великой Отечественной войне. «Мы движемся к 100-летию Бурятии. У нас пройдут большие мероприятия, мы готовим национальные балет и оперу. От лица всех, кто работает в культуре, благодарим вас – ветеранов – за вашу работу, за то, что вы у нас есть. Желаем вам крепкого здоровья и стойкости. И неспроста директором музея работает внучка Андрея Урупхеевича и эту выставку подготовил Национальный музей Бурятии. Я думаю, что в ближайшем будущем у нас подобных выставок будет больше, и имена ветеранов и Андрея Урупхеевича еще прозвучат не раз», &#8212; отметила она.</p>\n<p>Затем выступила директор Национального музея Татьяна Бороноева.</p>\n<p>– Добрый день, дорогие друзья! Мы рады приветствовать вас в нашем Музее истории Бурятии. Самым главным в наше время являются не мероприятия, а люди, которые формировали историю нашей республики. Это наша с вами история, поэтому мы назвали выставку «Человек – эпоха». Наши молодые сотрудники, формировавшие выставку, выбрали это название, поскольку жизнь Андрея Урупхеевича полностью была посвящена работе, людям в Бурятии. Он воспринимал себя неотрывно от этой жизни. Поэтому мы постарались собрать и фотографии, отражающие эту палитру, и вещи, принадлежавшие ему лично. Здесь можно найти предметы из нашего музея, знамёна того времени и БАМовские плакаты. Мы хотели, чтобы каждый, особенно молодежь, придя на выставку, мог окунуться в то время, Хотели, чтобы посетители почувствовали, как интересно и содержательно проходила жизнь. Спасибо вам большое, что вы пришли, несмотря на мороз. Хочу&nbsp; пожелать вам удачи здоровья и благополучия!, – рассказала директор музея.</p>\n<p>В экспозиции представлены фотографии и документы, которые расскажут о жизни и государственной деятельности Андрея Урупхеевича. Также, можно будет увидеть награды политического лидера, личные вещи, переданные в дар Национальному музею РБ семьей Модогоевых. На выставке представлен портрет Андрея Модогоева, написанный к 100-летию первого секретаря Бурятского обкома КПСС, заслуженным художником РБ, членом Союза художников Бурятии Нохоевой Л.И.</p>\n<p>Выставка будет работать до 15 февраля 2020 года.</p>\n<p>Музей истории Бурятии им. М.Н. Хангалова, ул. Профсоюзная, 29. Телефон для справок: 21-40-08.</p>\n<p>&nbsp;</p>\n<p>Андрей Урупхеевич Модогоев – советский государственный и партийный деятель, руководитель республики – первый секретарь Бурятского обкома КПСС (1962-1984).</p>\n<p>Родился 15 января 1915 года в крестьянской семье в улусе Загатуй Иркутской губернии (ныне с. Загатуй Баяндаевского района Иркутской области). После обучения в институте в Улан-Удэ работал учителем Загатуйской школы. Затем трудился бухгалтером, занимался комсомольской работой.</p>\n<p>30 декабря 1939 года был избран первым секретарём Улан-Удэнского горкома ВЛКСМ. В апреле 1940 года вступил в члены ВКП(б). С 1941 по 1944 годы – первый секретарь Бурят-Монгольского обкома ВЛКСМ. В дальнейшем работал на государственных и партийных постах.</p>\n<p>Широко известен благодаря тем, что под его руководством Бурятия совершила резкий скачок развития в производстве, сельском хозяйстве, культуре и социальном развитии. Под его руководством были запущены в эксплуатацию десятки новых предприятий – Селенгинский целлюлозно-картонный комбинат, Улан-Удэнский завод мостовых металлических конструкций, фабрика верхнего трикотажа, кондитерская фабрика, завод по переработке птицы на мясокомбинате и др. Большое внимание Андрей Урупхеевич уделял строительству Бурятского участка Байкало-Амурской магистрали. Благодаря его руководству вступили в строй Гусиноозёрская ГРЭС, ТЭЦ-2 в Улан-Удэ, Холбольджинский и Тугнуйский угольные разрезы и многие другие крупные производственные и инфраструктурные объекты.<br />\nС 1962 по 1984 годы – депутат Верховного Совета СССР. С 1984 года – персональный пенсионер союзного значения.</p>\n<p>Ушел из жизни 29 октября 1989 года.</p>\n<div class=\"b-gallery\"><a href='http://2020.muzeyrb.ru/wp-content/uploads/2020/01/chelovek_yepokha.jpg' rel='lightbox'><img src='http://2020.muzeyrb.ru/wp-content/uploads/2020/01/chelovek_yepokha-160x120.jpg' style='width:160px' class='b-gallery-el'/></a><a href='http://2020.muzeyrb.ru/wp-content/uploads/2020/01/image-15-01-20-06-15-17.jpeg' rel='lightbox'><img src='http://2020.muzeyrb.ru/wp-content/uploads/2020/01/image-15-01-20-06-15-17-160x120.jpeg' style='width:160px' class='b-gallery-el'/></a><a href='http://2020.muzeyrb.ru/wp-content/uploads/2020/01/image-15-01-20-06-14-1.jpeg' rel='lightbox'><img src='http://2020.muzeyrb.ru/wp-content/uploads/2020/01/image-15-01-20-06-14-1-160x120.jpeg' style='width:160px' class='b-gallery-el'/></a><a href='http://2020.muzeyrb.ru/wp-content/uploads/2020/01/image-15-01-20-06-14-4.jpeg' rel='lightbox'><img src='http://2020.muzeyrb.ru/wp-content/uploads/2020/01/image-15-01-20-06-14-4-160x120.jpeg' style='width:160px' class='b-gallery-el'/></a><a href='http://2020.muzeyrb.ru/wp-content/uploads/2020/01/image-15-01-20-06-14-7.jpeg' rel='lightbox'><img src='http://2020.muzeyrb.ru/wp-content/uploads/2020/01/image-15-01-20-06-14-7-160x120.jpeg' style='width:160px' class='b-gallery-el'/></a><a href='http://2020.muzeyrb.ru/wp-content/uploads/2020/01/image-15-01-20-06-15.jpeg' rel='lightbox'><img src='http://2020.muzeyrb.ru/wp-content/uploads/2020/01/image-15-01-20-06-15-160x120.jpeg' style='width:160px' class='b-gallery-el'/></a><a href='http://2020.muzeyrb.ru/wp-content/uploads/2020/01/image-15-01-20-06-15-4.jpeg' rel='lightbox'><img src='http://2020.muzeyrb.ru/wp-content/uploads/2020/01/image-15-01-20-06-15-4-160x120.jpeg' style='width:160px' class='b-gallery-el'/></a><a href='http://2020.muzeyrb.ru/wp-content/uploads/2020/01/image-15-01-20-06-15-14.jpeg' rel='lightbox'><img src='http://2020.muzeyrb.ru/wp-content/uploads/2020/01/image-15-01-20-06-15-14-160x120.jpeg' style='width:160px' class='b-gallery-el'/></a></div>\n<p>&nbsp;</p>\n<p>&nbsp;</p>\n"}